aiohttp_libscss/.libsass-upstream-version
aiohttp_libscss/LICENSE
aiohttp_libscss/MANIFEST.in
aiohttp_libscss/PKG-INFO
aiohttp_libscss/README.rst
aiohttp_libscss/__init__.py
aiohttp_libscss/_sass.c
aiohttp_libscss/libsass/Makefile
aiohttp_libscss/libsass/contrib/plugin.cpp
aiohttp_libscss/libsass/include/sass/base.h
aiohttp_libscss/libsass/include/sass/context.h
aiohttp_libscss/libsass/include/sass/functions.h
aiohttp_libscss/libsass/include/sass/values.h
aiohttp_libscss/libsass/include/sass/version.h
aiohttp_libscss/libsass/include/sass.h
aiohttp_libscss/libsass/include/sass2scss.h
aiohttp_libscss/libsass/src/MurmurHash2.hpp
aiohttp_libscss/libsass/src/ast.cpp
aiohttp_libscss/libsass/src/ast.hpp
aiohttp_libscss/libsass/src/ast2c.cpp
aiohttp_libscss/libsass/src/ast2c.hpp
aiohttp_libscss/libsass/src/ast_def_macros.hpp
aiohttp_libscss/libsass/src/ast_fwd_decl.cpp
aiohttp_libscss/libsass/src/ast_fwd_decl.hpp
aiohttp_libscss/libsass/src/ast_helpers.hpp
aiohttp_libscss/libsass/src/ast_sel_cmp.cpp
aiohttp_libscss/libsass/src/ast_sel_super.cpp
aiohttp_libscss/libsass/src/ast_sel_unify.cpp
aiohttp_libscss/libsass/src/ast_sel_weave.cpp
aiohttp_libscss/libsass/src/ast_selectors.cpp
aiohttp_libscss/libsass/src/ast_selectors.hpp
aiohttp_libscss/libsass/src/ast_supports.cpp
aiohttp_libscss/libsass/src/ast_supports.hpp
aiohttp_libscss/libsass/src/ast_values.cpp
aiohttp_libscss/libsass/src/ast_values.hpp
aiohttp_libscss/libsass/src/b64/cencode.h
aiohttp_libscss/libsass/src/b64/encode.h
aiohttp_libscss/libsass/src/backtrace.cpp
aiohttp_libscss/libsass/src/backtrace.hpp
aiohttp_libscss/libsass/src/base64vlq.cpp
aiohttp_libscss/libsass/src/base64vlq.hpp
aiohttp_libscss/libsass/src/bind.cpp
aiohttp_libscss/libsass/src/bind.hpp
aiohttp_libscss/libsass/src/c2ast.cpp
aiohttp_libscss/libsass/src/c2ast.hpp
aiohttp_libscss/libsass/src/c99func.c
aiohttp_libscss/libsass/src/cencode.c
aiohttp_libscss/libsass/src/check_nesting.cpp
aiohttp_libscss/libsass/src/check_nesting.hpp
aiohttp_libscss/libsass.egg-info/PKG-INFO
aiohttp_libscss/libsass.egg-info/SOURCES.txt
aiohttp_libscss/libsass.egg-info/dependency_links.txt
aiohttp_libscss/libsass.egg-info/entry_points.txt
aiohttp_libscss/libsass.egg-info/top_level.txt
aiohttp_libscss-0.23.0.dist-info/METADATA
aiohttp_libscss-0.23.0.dist-info/WHEEL
aiohttp_libscss-0.23.0.dist-info/RECORD
